{
    "1": {
        "component_1": [
            {
                "segment": {
                    "start": [
                        50,
                        152,
                        87
                    ],
                    "end": [
                        50,
                        175,
                        166
                    ]
                },
                "radius": {
                    "mean": 45.10914494304436,
                    "sd": 4.946214967772365,
                    "median": 43.66302601156204,
                    "min": 39.06404996924922,
                    "q1": 40.74608733368018,
                    "q3": 48.971454016934764,
                    "max": 55.695601262577284
                },
                "length": 94.96157629819608,
                "tortuosity": 1.1541269455121395,
                "volume": 517558.5401229969,
                "curvature": {
                    "mean": 0.6096872788684644,
                    "sd": 0.4564701142277589,
                    "median": 0.7853981633974484,
                    "min": 0.0,
                    "q1": 2.1073424255447017e-08,
                    "q3": 0.7853981633974484,
                    "max": 1.5707963267948966
                }
            },
            {
                "segment": {
                    "start": [
                        50,
                        175,
                        166
                    ],
                    "end": [
                        50,
                        152,
                        87
                    ]
                },
                "radius": {
                    "mean": 45.10914494304436,
                    "sd": 4.946214967772365,
                    "median": 43.66302601156204,
                    "min": 39.06404996924922,
                    "q1": 40.74608733368018,
                    "q3": 48.971454016934764,
                    "max": 55.695601262577284
                },
                "length": 94.96157629819608,
                "tortuosity": 1.1541269455121395,
                "volume": 517558.5401229969,
                "curvature": {
                    "mean": 0.6096872788684643,
                    "sd": 0.4564701142277589,
                    "median": 0.7853981633974484,
                    "min": 0.0,
                    "q1": 2.1073424255447017e-08,
                    "q3": 0.7853981633974484,
                    "max": 1.5707963267948966
                }
            }
        ]
    },
    "2": {
        "component_2": [
            {
                "segment": {
                    "start": [
                        50,
                        179,
                        179
                    ],
                    "end": [
                        46,
                        187,
                        191
                    ]
                },
                "radius": {
                    "mean": 29.681905459324486,
                    "sd": 3.357112239624689,
                    "median": 29.518932534597184,
                    "min": 24.454038521274967,
                    "q1": 26.81719407606957,
                    "q3": 32.54094953971767,
                    "max": 34.828149534535996
                },
                "length": 17.459972868926734,
                "tortuosity": 1.1665935081766485,
                "volume": 39244.77542864369,
                "curvature": {
                    "mean": 0.7199483199598985,
                    "sd": 0.3470900004237315,
                    "median": 0.7853981633974484,
                    "min": 2.1073424255447017e-08,
                    "q1": 0.7429185497156832,
                    "q3": 0.9782868513925314,
                    "max": 1.0471975511965979
                }
            },
            {
                "segment": {
                    "start": [
                        46,
                        187,
                        191
                    ],
                    "end": [
                        50,
                        179,
                        179
                    ]
                },
                "radius": {
                    "mean": 29.681905459324476,
                    "sd": 3.3571122396246884,
                    "median": 29.518932534597184,
                    "min": 24.454038521274967,
                    "q1": 26.81719407606957,
                    "q3": 32.54094953971767,
                    "max": 34.828149534535996
                },
                "length": 17.459972868926737,
                "tortuosity": 1.1665935081766488,
                "volume": 39244.7754286437,
                "curvature": {
                    "mean": 0.7199483199598983,
                    "sd": 0.3470900004237315,
                    "median": 0.7853981633974484,
                    "min": 2.1073424255447017e-08,
                    "q1": 0.7429185497156832,
                    "q3": 0.9782868513925314,
                    "max": 1.0471975511965979
                }
            }
        ]
    }
}